maos/__init__.py
maos/agents/templates/__init__.py
maos/agents/templates/agent_templates.py
maos/api/__init__.py
maos/api/claude_integration.py
maos/api/rest_api.py
maos/api/schemas.py
maos/cli/__init__.py
maos/cli/_main.py
maos/cli/completion.py
maos/cli/config.py
maos/cli/formatters.py
maos/cli/interactive.py
maos/cli/main.py
maos/cli/monitoring.py
maos/cli/natural_language.py
maos/cli/natural_language_v2.py
maos/cli/natural_language_v3.py
maos/cli/natural_language_v7.py
maos/cli/session_commands.py
maos/cli/commands/agent.py
maos/cli/commands/config.py
maos/cli/commands/orchestration.py
maos/cli/commands/recover.py
maos/cli/commands/status.py
maos/cli/commands/task.py
maos/core/__init__.py
maos/core/agent_discovery.py
maos/core/agent_manager.py
maos/core/agent_message_bus.py
maos/core/claude_cli_manager.py
maos/core/claude_sdk_executor.py
maos/core/claude_sdk_manager.py
maos/core/claude_subagent_manager.py
maos/core/context_manager.py
maos/core/coordinator_agent.py
maos/core/execution_explainer.py
maos/core/intelligent_decomposer.py
maos/core/maos_config.py
maos/core/orchestrated_agent.py
maos/core/orchestrator.py
maos/core/orchestrator_brain.py
maos/core/orchestrator_brain_v2.py
maos/core/orchestrator_v7.py
maos/core/persistent_message_bus.py
maos/core/resource_allocator.py
maos/core/session_manager.py
maos/core/session_manager_lite.py
maos/core/session_manager_v2.py
maos/core/swarm_coordinator.py
maos/core/task_decomposer.py
maos/core/task_decomposer_v2.py
maos/core/task_planner.py
maos/interfaces/__init__.py
maos/interfaces/claude_commands.py
maos/interfaces/message_bus.py
maos/interfaces/orchestrator_interface.py
maos/interfaces/persistence.py
maos/interfaces/redis_message_bus.py
maos/interfaces/redis_persistence.py
maos/interfaces/redis_persistence_full.py
maos/interfaces/sqlite_persistence.py
maos/interfaces/state_manager.py
maos/models/__init__.py
maos/models/agent.py
maos/models/checkpoint.py
maos/models/claude_agent_process.py
maos/models/message.py
maos_cli-0.9.4.dist-info/METADATA
maos_cli-0.9.4.dist-info/WHEEL
maos_cli-0.9.4.dist-info/entry_points.txt
maos_cli-0.9.4.dist-info/licenses/LICENSE
maos_cli-0.9.4.dist-info/RECORD
