Metadata-Version: 2.4
Name: maos-cli
Version: 0.9.4
Summary: Orchestrate swarms of Claude subagents with natural language
Project-URL: Homepage, https://github.com/vincentsider/maos-cli
Project-URL: Documentation, https://github.com/vincentsider/maos-cli#readme
Project-URL: Repository, https://github.com/vincentsider/maos-cli
Project-URL: Issues, https://github.com/vincentsider/maos-cli/issues
Project-URL: Source Code, https://github.com/vincentsider/maos-cli
Author-email: Vincent Sider <vincent@maos.dev>
Maintainer-email: Vincent Sider <vincent@maos.dev>
License: MIT
License-File: LICENSE
Keywords: agents,ai,automation,claude,llm,orchestration,sdk,swarm
Classifier: Development Status :: 3 - Alpha
Classifier: Environment :: Console
Classifier: Intended Audience :: Developers
Classifier: License :: OSI Approved :: MIT License
Classifier: Natural Language :: English
Classifier: Operating System :: OS Independent
Classifier: Programming Language :: Python :: 3
Classifier: Programming Language :: Python :: 3.11
Classifier: Programming Language :: Python :: 3.12
Classifier: Topic :: Scientific/Engineering :: Artificial Intelligence
Classifier: Topic :: Software Development :: Libraries :: Python Modules
Classifier: Topic :: System :: Distributed Computing
Requires-Python: >=3.11
Requires-Dist: aiofiles>=23.2.1
Requires-Dist: aiosqlite>=0.19.0
Requires-Dist: psutil>=5.9.0
Requires-Dist: python-dotenv>=1.0.0
Requires-Dist: pyyaml>=6.0.1
Requires-Dist: rich>=13.7.0
Requires-Dist: typer>=0.9.0
Provides-Extra: api
Requires-Dist: fastapi>=0.104.1; extra == 'api'
Requires-Dist: httpx>=0.25.2; extra == 'api'
Requires-Dist: pydantic>=2.5.0; extra == 'api'
Requires-Dist: uvicorn[standard]>=0.24.0; extra == 'api'
Provides-Extra: dev
Requires-Dist: black>=23.11.0; extra == 'dev'
Requires-Dist: mypy>=1.7.1; extra == 'dev'
Requires-Dist: pytest-asyncio>=0.21.1; extra == 'dev'
Requires-Dist: pytest-cov>=4.1.0; extra == 'dev'
Requires-Dist: pytest>=7.4.3; extra == 'dev'
Requires-Dist: ruff>=0.1.6; extra == 'dev'
Provides-Extra: full
Requires-Dist: aioredis>=2.0.1; extra == 'full'
Requires-Dist: cryptography>=41.0.7; extra == 'full'
Requires-Dist: fastapi>=0.104.1; extra == 'full'
Requires-Dist: httpx>=0.25.2; extra == 'full'
Requires-Dist: prometheus-client>=0.19.0; extra == 'full'
Requires-Dist: pydantic>=2.5.0; extra == 'full'
Requires-Dist: pyjwt>=2.8.0; extra == 'full'
Requires-Dist: redis>=5.0.1; extra == 'full'
Requires-Dist: sqlalchemy[asyncio]>=2.0.23; extra == 'full'
Requires-Dist: uvicorn[standard]>=0.24.0; extra == 'full'
Provides-Extra: redis
Requires-Dist: aioredis>=2.0.1; extra == 'redis'
Requires-Dist: redis>=5.0.1; extra == 'redis'
